lr_dmx/__init__.py
lr_dmx/cli.py
lr_dmx/constants.py
lr_dmx/receive-dmx.py
lr_dmx/receiver.py
lr_dmx/send-dmx.py
lr_dmx/transmitter.py
lr_dmx-0.2.2.dist-info/METADATA
lr_dmx-0.2.2.dist-info/WHEEL
lr_dmx-0.2.2.dist-info/entry_points.txt
lr_dmx-0.2.2.dist-info/RECORD
