Metadata-Version: 2.4
Name: lr-dmx
Version: 0.2.2
Summary: DMX512 helpers for FT231XS-based RS-485 HIL setups
Author-email: Jonas Estberger <jonas.estberger@lumenradio.com>
License: MIT
Requires-Python: >=3.9
Requires-Dist: pyserial>=3.5
Provides-Extra: dev
Requires-Dist: black>=25.9.0; extra == 'dev'
Requires-Dist: build>=1.2.1; extra == 'dev'
Requires-Dist: pytest-cov>=4.0; extra == 'dev'
Requires-Dist: pytest>=7.0; extra == 'dev'
Requires-Dist: twine>=5.1.1; extra == 'dev'
